{
  "version": 3,
  "middleware": {
    "/": {
      "files": [
        "server/edge/chunks/_8be0af29._.js",
        "server/edge/chunks/[root-of-the-server]__de110ef0._.js",
        "server/edge/chunks/edge-wrapper_d61ed9c1.js"
      ],
      "name": "middleware",
      "page": "/",
      "matchers": [
        {
          "regexp": "^(?:\\/(_next\\/data\\/[^/]{1,}))?(?:\\/((?!_next|[^?]*\\.(?:html?|css|js(?!on)|jpe?g|webp|png|gif|svg|ttf|woff2?|ico|csv|docx?|xlsx?|zip|webmanifest)).*))(\\\\.json)?[\\/#\\?]?$",
          "originalSource": "/((?!_next|[^?]*\\.(?:html?|css|js(?!on)|jpe?g|webp|png|gif|svg|ttf|woff2?|ico|csv|docx?|xlsx?|zip|webmanifest)).*)"
        },
        {
          "regexp": "^(?:\\/(_next\\/data\\/[^/]{1,}))?(?:\\/(api|trpc))(.*)(\\\\.json)?[\\/#\\?]?$",
          "originalSource": "/(api|trpc)(.*)"
        },
        {
          "regexp": "^(?:\\/(_next\\/data\\/[^/]{1,}))?(?:\\/((?!_next|api|trpc).*))(\\\\.json)?[\\/#\\?]?$",
          "originalSource": "/((?!_next|api|trpc).*)"
        }
      ],
      "wasm": [],
      "assets": [],
      "env": {
        "__NEXT_BUILD_ID": "development",
        "NEXT_SERVER_ACTIONS_ENCRYPTION_KEY": "VdSqtc972gOTSI74jHqD8rLz/kLCepdt5XVqcbmsV6s=",
        "__NEXT_PREVIEW_MODE_ID": "79ae80f949715dadc08f2ee7252a5b12",
        "__NEXT_PREVIEW_MODE_ENCRYPTION_KEY": "f7160c62ac4c4ee3e0cd1c735a5868ddfa2ae28277675be9a729869c7d352e2b",
        "__NEXT_PREVIEW_MODE_SIGNING_KEY": "8ac4a40c0094a78846b2b37569a5657c5cfe5fded2988f3d48982cbebf3ad0dd"
      }
    }
  },
  "sortedMiddleware": [
    "/"
  ],
  "functions": {}
}